{
  "company_name": "台積電",
  "ticker": "",
  "industry": "其他",
  "report_year": 2024,
  "report_title": "台積電2024年永續報告書",
  "indicators": {
    "ghg_scope1": {
      "value": 1825872,
      "source_text": "台灣廠區(公噸) 244,560\n子公司(公噸) 1,581,312",
      "unit": "公噸CO2e",
      "source_page": 266,
      "confidence": 0.95,
      "_compact_page": 34,
      "bbox": [
        0.8395,
        0.6543,
        0.8842,
        0.6793
      ],
      "_pdf_page": 119
    },
    "ghg_scope2": {
      "value": 10957397,
      "source_text": "台灣廠區(公噸) 30,753\n子公司(公噸) 10,926,644",
      "unit": "公噸CO2e",
      "source_page": 266,
      "confidence": 0.95,
      "_compact_page": 34,
      "bbox": [
        0.8472,
        0.7079,
        0.8976,
        0.7329
      ],
      "_pdf_page": 119
    },
    "ghg_scope3": {
      "value": 8219871,
      "source_text": "購買產品及服務 3,284\n燃料與能源相關活動(非範疇一/二部分) 40,017\n營運產生的廢棄物處理 1,211\n上游(原物料)運輸及分配 1,427\n下游(產品)運輸及分配 58,775\n員工通勤 2,458,773\n商務旅行 5,656,384",
      "unit": "公噸CO2e",
      "source_page": 266,
      "confidence": 0.95,
      "_compact_page": 30,
      "bbox": [
        [
          0.8711,
          0.2503,
          0.8755,
          0.2697
        ],
        [
          0.8668,
          0.288,
          0.8755,
          0.3073
        ],
        [
          0.8711,
          0.3069,
          0.8755,
          0.3262
        ],
        [
          0.8711,
          0.3257,
          0.8755,
          0.3451
        ],
        [
          0.8668,
          0.3446,
          0.8755,
          0.3639
        ],
        [
          0.8562,
          0.3635,
          0.8605,
          0.3828
        ],
        [
          0.855,
          0.3823,
          0.8594,
          0.4016
        ]
      ],
      "_pdf_page": 115
    },
    "carbon_intensity": {
      "value": null,
      "source_text": null,
      "unit": "公噸CO2e/百萬元",
      "source_page": 260,
      "confidence": 0.0,
      "_compact_page": null,
      "bbox": null
    },
    "electricity": {
      "value": 25534080000,
      "source_text": "能源總消耗量為274.56億度,外購電力約占93.0%",
      "unit": "kWh",
      "source_page": 267,
      "confidence": 0.95,
      "_compact_page": 34,
      "bbox": [
        [
          0.0471,
          0.2376,
          0.0657,
          0.2653
        ],
        [
          0.1906,
          0.2376,
          0.2031,
          0.2653
        ]
      ],
      "_pdf_page": 120
    },
    "renewable_ratio": {
      "value": 14.1,
      "source_text": "14.1%",
      "unit": "%",
      "source_page": 267,
      "confidence": 0.95,
      "_compact_page": 23,
      "bbox": [
        0.621,
        0.6325,
        0.6491,
        0.6576
      ],
      "_pdf_page": 108
    },
    "water": {
      "value": 161000000,
      "source_text": "台積公司自來水總用量(百萬立方公尺) 161.0",
      "unit": "立方公尺",
      "source_page": 267,
      "confidence": 0.95,
      "_compact_page": 43,
      "bbox": null,
      "_pdf_page": 129
    },
    "waste": {
      "value": null,
      "source_text": null,
      "unit": "公噸",
      "source_page": 268,
      "confidence": 0.0,
      "_compact_page": null,
      "bbox": null
    },
    "injury_rate": {
      "value": 0.26,
      "source_text": "0.26",
      "unit": "TRIR",
      "source_page": 270,
      "confidence": 0.95,
      "_compact_page": 65,
      "bbox": null,
      "_pdf_page": 187
    },
    "turnover": {
      "value": 3.5,
      "source_text": "3.5%",
      "unit": "%",
      "source_page": 270,
      "confidence": 0.95,
      "_compact_page": 54,
      "bbox": null,
      "_pdf_page": 166
    },
    "female_ratio": {
      "value": 33.7,
      "source_text": "33.7%",
      "unit": "%",
      "source_page": 269,
      "confidence": 0.95,
      "_compact_page": 51,
      "bbox": null,
      "_pdf_page": 161
    },
    "female_mgmt_ratio": {
      "value": 15.0,
      "source_text": "15.0%",
      "unit": "%",
      "source_page": 269,
      "confidence": 0.95,
      "_compact_page": 51,
      "bbox": null,
      "_pdf_page": 161
    },
    "training_hours": {
      "value": 100.5,
      "source_text": "100.5 小時",
      "unit": "小時/人/年",
      "source_page": 270,
      "confidence": 0.95,
      "_compact_page": 45,
      "bbox": [
        0.0471,
        0.5367,
        0.123,
        0.6145
      ],
      "_pdf_page": 154
    },
    "independent_director_ratio": {
      "value": 70.0,
      "source_text": "7位獨立董事",
      "unit": "%",
      "source_page": 263,
      "confidence": 0.95,
      "_compact_page": 72,
      "bbox": null,
      "_pdf_page": 234
    },
    "female_director_ratio": {
      "value": 20.0,
      "source_text": "2名女性董事",
      "unit": "%",
      "source_page": 263,
      "confidence": 0.95,
      "_compact_page": 72,
      "bbox": null,
      "_pdf_page": 234
    },
    "has_sustainability_officer": {
      "value": false,
      "source_text": null,
      "unit": "布林",
      "source_page": 254,
      "confidence": 0.0,
      "_compact_page": null,
      "bbox": null
    },
    "assurance": {
      "value": true,
      "source_text": "Taiwan Semiconductor Manufacturing Company Ltd. ('TSMC' or 'the Company') commissioned DNV Business Assurance Co. Ltd. (\"DNV\") to undertake independent assurance of the 2024 Sustainability Report (the \"Report\") for the year ended 31 December 2024.",
      "unit": "布林",
      "source_page": 276,
      "confidence": 0.95,
      "_compact_page": 82,
      "bbox": null,
      "_pdf_page": 276
    },
    "violations": {
      "value": 0,
      "source_text": "民國113年台積公司無任何重大(罰款超過新台幣100萬元)的違法情事",
      "unit": "次",
      "source_page": 258,
      "confidence": 0.95,
      "_compact_page": 65,
      "bbox": null,
      "_pdf_page": 187
    }
  },
  "greenwash_claims": [],
  "_meta": {
    "pipeline_version": "v2-hybrid",
    "total_pdf_pages": 278,
    "compact_pdf_pages": 84,
    "page_offset": 19,
    "compact_page_map": {
      "1": 19,
      "2": 20,
      "3": 21,
      "4": 23,
      "5": 24,
      "6": 25,
      "7": 28,
      "8": 29,
      "9": 30,
      "10": 39,
      "11": 40,
      "12": 41,
      "13": 97,
      "14": 98,
      "15": 99,
      "16": 100,
      "17": 102,
      "18": 103,
      "19": 104,
      "20": 105,
      "21": 106,
      "22": 107,
      "23": 108,
      "24": 109,
      "25": 110,
      "26": 111,
      "27": 112,
      "28": 113,
      "29": 114,
      "30": 115,
      "31": 116,
      "32": 117,
      "33": 118,
      "34": 119,
      "35": 120,
      "36": 121,
      "37": 123,
      "38": 124,
      "39": 125,
      "40": 126,
      "41": 127,
      "42": 128,
      "43": 129,
      "44": 130,
      "45": 154,
      "46": 155,
      "47": 156,
      "48": 158,
      "49": 159,
      "50": 160,
      "51": 161,
      "52": 162,
      "53": 165,
      "54": 166,
      "55": 167,
      "56": 173,
      "57": 174,
      "58": 175,
      "59": 176,
      "60": 177,
      "61": 183,
      "62": 184,
      "63": 185,
      "64": 186,
      "65": 187,
      "66": 188,
      "67": 193,
      "68": 194,
      "69": 195,
      "70": 196,
      "71": 233,
      "72": 234,
      "73": 235,
      "74": 236,
      "75": 244,
      "76": 245,
      "77": 246,
      "78": 272,
      "79": 273,
      "80": 274,
      "81": 275,
      "82": 276,
      "83": 277,
      "84": 278
    },
    "gri_page_map": {
      "ghg_scope1": [
        266
      ],
      "ghg_scope2": [
        266
      ],
      "ghg_scope3": [
        266
      ],
      "carbon_intensity": [
        260
      ],
      "electricity": [
        267
      ],
      "renewable_ratio": [
        267
      ],
      "water": [
        267
      ],
      "waste": [
        268
      ],
      "injury_rate": [
        270
      ],
      "turnover": [
        270
      ],
      "female_ratio": [
        269
      ],
      "female_mgmt_ratio": [
        269
      ],
      "training_hours": [
        270
      ],
      "independent_director_ratio": [
        263
      ],
      "female_director_ratio": [
        263
      ],
      "has_sustainability_officer": [
        254,
        256
      ],
      "assurance": [
        276
      ],
      "violations": [
        258
      ]
    },
    "indicators_found": 16,
    "pdf_path": "C:\\Users\\QuzzS\\Desktop\\Code_114-2\\esg-risk-system\\data\\pdfs\\台積電_2024.pdf"
  }
}